SlideLocalAPI/SlideLocalAPI.py
SlideLocalAPI/__init__.py
SlideLocalAPI-0.3.0.dist-info/LICENSE
SlideLocalAPI-0.3.0.dist-info/METADATA
SlideLocalAPI-0.3.0.dist-info/WHEEL
SlideLocalAPI-0.3.0.dist-info/top_level.txt
SlideLocalAPI-0.3.0.dist-info/RECORD
